cli/__init__.py
cli/main.py
network_importer_rest-0.0.8.dist-info/licenses/LICENSE
ni_rest/__init__.py
ni_rest/manage.py
ni_rest/api/__init__.py
ni_rest/api/admin.py
ni_rest/api/apps.py
ni_rest/api/models.py
ni_rest/api/serializers.py
ni_rest/api/tasks.py
ni_rest/api/tests.py
ni_rest/api/urls.py
ni_rest/api/utils.py
ni_rest/api/views.py
ni_rest/api/migrations/0001_initial.py
ni_rest/api/migrations/__init__.py
ni_rest/api/services/__init__.py
ni_rest/api/services/config_generator.py
ni_rest/api/services/job_logger.py
ni_rest/api/services/ni_service.py
ni_rest/core/__init__.py
ni_rest/core/asgi.py
ni_rest/core/celery.py
ni_rest/core/db_utils.py
ni_rest/core/settings.py
ni_rest/core/urls.py
ni_rest/core/wsgi.py
network_importer_rest-0.0.8.dist-info/METADATA
network_importer_rest-0.0.8.dist-info/WHEEL
network_importer_rest-0.0.8.dist-info/entry_points.txt
network_importer_rest-0.0.8.dist-info/top_level.txt
network_importer_rest-0.0.8.dist-info/RECORD
