Metadata-Version: 2.4
Name: network-importer-rest
Version: 0.0.8
Summary: A REST API wrapper around network-importer
Author-email: André Lima <andre@netcube.consulting>
License: Apache-2.0
Requires-Python: >=3.11
License-File: LICENSE
Requires-Dist: django>=5.2.3
Requires-Dist: django-filter>=25.1
Requires-Dist: djangorestframework>=3.16.0
Requires-Dist: python-dotenv>=1.0.0
Requires-Dist: typer>=0.12.0
Requires-Dist: network-importer
Requires-Dist: rich>=14.0.0
Requires-Dist: celery>=5.3.0
Requires-Dist: redis>=5.0.0
Requires-Dist: django-celery-results>=2.5.0
Requires-Dist: drf-spectacular>=0.27.0
Requires-Dist: psutil>=5.9.0
Requires-Dist: dj-database-url>=3.0.1
Provides-Extra: postgres
Requires-Dist: psycopg[binary]>=3.1; extra == "postgres"
Dynamic: license-file
